segment_animals/__init__.py
segment_animals/detect.py
segment_animals/model_cache.py
segment_animals/models.py
segment_animals/segment.py
segment_animals/util.py
segment_animals/viz.py
segment_animals-1.0.0.dist-info/METADATA
segment_animals-1.0.0.dist-info/WHEEL
segment_animals-1.0.0.dist-info/entry_points.txt
segment_animals-1.0.0.dist-info/RECORD
