Metadata-Version: 2.4
Name: segment-animals
Version: 1.0.0
Summary: Segment (Extract) Animals from Images - Removing Background
Author-email: Ben Evans <ben@bluechimp.io>
Requires-Python: >=3.10
Requires-Dist: megadetector>=5.0.29
Requires-Dist: pillow>=11.2.1
Requires-Dist: requests>=2.32.4
Requires-Dist: segment-anything
